{"Cetus Bounty Rewards":[{"Level 5 - 15 Orb Vallis Bounty":[
		{"Rotation A":[{"Stage 1":{"100X Oxium":"Uncommon (20.00%)","1,500 Credits Cache":"Uncommon (20.00%)","50 Endo":"Uncommon (20.00%)","5X Mytocardia Spore":"Uncommon (20.00%)","2X Training Debt-Bond":"Uncommon (20.00%)"}},{"Stage 2, Stage 3 of 4, and Stage 3 of 5":{"100X Oxium":"Uncommon (15.49%)","1,500 Credits Cache":"Uncommon (15.49%)","50 Endo":"Uncommon (15.49%)","5X Mytocardia Spore":"Uncommon (15.49%)","2X Training Debt-Bond":"Uncommon (15.49%)","Garuda Chassis Blueprint":"Rare (7.52%)","5X Tepa Nodule":"Rare (7.52%)","3,000 Credits Cache":"Rare (7.52%)"}},{"Stage 4 of 5":{"100X Oxium":"Uncommon (15.18%)","1,500 Credits Cache":"Uncommon (15.18%)","50 Endo":"Uncommon (15.18%)","5X Mytocardia Spore":"Uncommon (15.18%)","2X Training Debt-Bond":"Uncommon (15.18%)","Garuda Chassis Blueprint":"Rare (7.37%)","5X Tepa Nodule":"Rare (7.37%)","3,000 Credits Cache":"Rare (7.37%)","Lith M4 Relic":"Rare (2.01%)"}},{"Final Stage":{"Garuda Chassis Blueprint":"Uncommon (30.56%)","5X Tepa Nodule":"Uncommon (30.56%)","3,000 Credits Cache":"Uncommon (30.56%)","Lith M4 Relic":"Rare (8.33%)"}}]},
		{"Rotation B":[{"Stage 1":{"100X Cryotic":"Uncommon (20.00%)","1,500 Credits Cache":"Uncommon (20.00%)","50 Endo":"Uncommon (20.00%)","5X Thermal Sludge":"Uncommon (20.00%)","2X Training Debt-Bond":"Uncommon (20.00%)"}},{"Stage 2, Stage 3 of 4, and Stage 3 of 5":{"100X Cryotic":"Uncommon (15.49%)","1,500 Credits Cache":"Uncommon (15.49%)","50 Endo":"Uncommon (15.49%)","5X Thermal Sludge":"Uncommon (15.49%)","2X Training Debt-Bond":"Uncommon (15.49%)","Garuda Chassis Blueprint":"Rare (7.52%)","5X Tepa Nodule":"Rare (7.52%)","3,000 Credits Cache":"Rare (7.52%)"}},{"Stage 4 of 5":{"100X Cryotic":"Uncommon (15.18%)","1,500 Credits Cache":"Uncommon (15.18%)","50 Endo":"Uncommon (15.18%)","5X Thermal Sludge":"Uncommon (15.18%)","2X Training Debt-Bond":"Uncommon (15.18%)","Garuda Chassis Blueprint":"Rare (7.37%)","5X Tepa Nodule":"Rare (7.37%)","3,000 Credits Cache":"Rare (7.37%)","Lith A3 Relic":"Rare (2.01%)"}},{"Final Stage":{"Garuda Chassis Blueprint":"Uncommon (30.56%)","5X Tepa Nodule":"Uncommon (30.56%)","3,000 Credits Cache":"Uncommon (30.56%)","Lith A3 Relic":"Rare (8.33%)"}}]},
		{"Rotation C":[{"Stage 1":{"100X Plastids":"Uncommon (20.00%)","1,500 Credits Cache":"Uncommon (20.00%)","50 Endo":"Uncommon (20.00%)","5X Gorgaricus Spore":"Uncommon (20.00%)","2X Training Debt-Bond":"Uncommon (20.00%)"}},{"Stage 2, Stage 3 of 4, and Stage 3 of 5":{"100X Plastids":"Uncommon (15.49%)","1,500 Credits Cache":"Uncommon (15.49%)","50 Endo":"Uncommon (15.49%)","5X Gorgaricus Spore":"Uncommon (15.49%)","2X Training Debt-Bond":"Uncommon (15.49%)","Garuda Chassis Blueprint":"Rare (7.52%)","5X Tepa Nodule":"Rare (7.52%)","3,000 Credits Cache":"Rare (7.52%)"}},{"Stage 4 of 5":{"100X Plastids":"Uncommon (15.18%)","1,500 Credits Cache":"Uncommon (15.18%)","50 Endo":"Uncommon (15.18%)","5X Gorgaricus Spore":"Uncommon (15.18%)","2X Training Debt-Bond":"Uncommon (15.18%)","Garuda Chassis Blueprint":"Rare (7.37%)","5X Tepa Nodule":"Rare (7.37%)","3,000 Credits Cache":"Rare (7.37%)","Lith P2 Relic":"Rare (2.01%)"}},{"Final Stage":{"Garuda Chassis Blueprint":"Uncommon (30.56%)","5X Tepa Nodule":"Uncommon (30.56%)","3,000 Credits Cache":"Uncommon (30.56%)","Lith P2 Relic":"Rare (8.33%)"}}]}]},{"Level 10 - 30 Orb Vallis Bounty":[
		{"Rotation A":[{"Stage 1":{"15X Mytocardia Spore":"Uncommon (20.00%)","200X Oxium":"Uncommon (20.00%)","2,500 Credits Cache":"Uncommon (20.00%)","100 Endo":"Uncommon (20.00%)","2X Shelter Debt-Bond":"Uncommon (20.00%)"}},{"Stage 2, Stage 3 of 4, and Stage 3 of 5":{"15X Mytocardia Spore":"Uncommon (14.81%)","200X Oxium":"Uncommon (14.81%)","2,500 Credits Cache":"Uncommon (14.81%)","100 Endo":"Uncommon (14.81%)","2X Shelter Debt-Bond":"Uncommon (14.81%)","Garuda Systems Blueprint":"Rare (7.41%)","5X Tepa Nodule":"Rare (7.41%)","Lith M4 Relic":"Uncommon (11.11%)"}},{"Stage 4 of 5":{"15X Mytocardia Spore":"Uncommon (13.79%)","200X Oxium":"Uncommon (13.79%)","2,500 Credits Cache":"Uncommon (13.79%)","100 Endo":"Uncommon (13.79%)","2X Shelter Debt-Bond":"Uncommon (13.79%)","Garuda Systems Blueprint":"Rare (6.90%)","5X Tepa Nodule":"Rare (6.90%)","Lith M4 Relic":"Uncommon (10.34%)","Synth Charge":"Rare (6.90%)"}},{"Final Stage":{"Garuda Systems Blueprint":"Uncommon (22.22%)","5X Tepa Nodule":"Uncommon (22.22%)","Lith M4 Relic":"Common (33.33%)","Synth Charge":"Uncommon (22.22%)"}}]},
		{"Rotation B":[{"Stage 1":{"15X Thermal Sludge":"Uncommon (20.00%)","200X Cryotic":"Uncommon (20.00%)","2,500 Credits Cache":"Uncommon (20.00%)","100 Endo":"Uncommon (20.00%)","2X Shelter Debt-Bond":"Uncommon (20.00%)"}},{"Stage 2, Stage 3 of 4, and Stage 3 of 5":{"15X Thermal Sludge":"Uncommon (14.81%)","200X Cryotic":"Uncommon (14.81%)","2,500 Credits Cache":"Uncommon (14.81%)","100 Endo":"Uncommon (14.81%)","2X Shelter Debt-Bond":"Uncommon (14.81%)","Garuda Systems Blueprint":"Rare (7.41%)","5X Tepa Nodule":"Rare (7.41%)","Lith A3 Relic":"Uncommon (11.11%)"}},{"Stage 4 of 5":{"15X Thermal Sludge":"Uncommon (13.79%)","200X Cryotic":"Uncommon (13.79%)","2,500 Credits Cache":"Uncommon (13.79%)","100 Endo":"Uncommon (13.79%)","2X Shelter Debt-Bond":"Uncommon (13.79%)","Garuda Systems Blueprint":"Rare (6.90%)","5X Tepa Nodule":"Rare (6.90%)","Lith A3 Relic":"Uncommon (10.34%)","Mecha Overdrive":"Rare (6.90%)"}},{"Final Stage":{"Garuda Systems Blueprint":"Uncommon (22.22%)","5X Tepa Nodule":"Uncommon (22.22%)","Lith A3 Relic":"Common (33.33%)","Mecha Overdrive":"Uncommon (22.22%)"}}]},
		{"Rotation C":[{"Stage 1":{"15X Gorgaricus Spore":"Uncommon (20.00%)","200X Nano Spores":"Uncommon (20.00%)","2,500 Credits Cache":"Uncommon (20.00%)","100 Endo":"Uncommon (20.00%)","2X Shelter Debt-Bond":"Uncommon (20.00%)"}},{"Stage 2, Stage 3 of 4, and Stage 3 of 5":{"15X Gorgaricus Spore":"Uncommon (14.81%)","200X Nano Spores":"Uncommon (14.81%)","2,500 Credits Cache":"Uncommon (14.81%)","100 Endo":"Uncommon (14.81%)","2X Shelter Debt-Bond":"Uncommon (14.81%)","Garuda Systems Blueprint":"Rare (7.41%)","5X Tepa Nodule":"Rare (7.41%)","Lith P2 Relic":"Uncommon (11.11%)"}},{"Stage 4 of 5":{"15X Gorgaricus Spore":"Uncommon (13.79%)","200X Nano Spores":"Uncommon (13.79%)","2,500 Credits Cache":"Uncommon (13.79%)","100 Endo":"Uncommon (13.79%)","2X Shelter Debt-Bond":"Uncommon (13.79%)","Garuda Systems Blueprint":"Rare (6.90%)","5X Tepa Nodule":"Rare (6.90%)","Lith P2 Relic":"Uncommon (10.34%)","Tek Assault":"Rare (6.90%)"}},{"Final Stage":{"Garuda Systems Blueprint":"Uncommon (22.22%)","5X Tepa Nodule":"Uncommon (22.22%)","Lith P2 Relic":"Common (33.33%)","Tek Assault":"Uncommon (22.22%)"}}]}]},{"Level 20 - 40 Orb Vallis Bounty":[
		{"Rotation A":[{"Stage 1":{"Madurai Lens":"Uncommon (20.00%)","200 Endo":"Common (40.00%)","300X Circuits":"Uncommon (20.00%)","2X Medical Debt-Bond":"Uncommon (20.00%)"}},{"Stage 2, Stage 3 of 4, and Stage 3 of 5":{"Madurai Lens":"Uncommon (12.50%)","200 Endo":"Uncommon (25.00%)","300X Circuits":"Uncommon (12.50%)","2X Medical Debt-Bond":"Uncommon (12.50%)","Garuda Neuroptics Blueprint":"Uncommon (12.50%)","Meso M3 Relic":"Uncommon (25.00%)"}},{"Stage 4 of 5":{"Madurai Lens":"Uncommon (11.11%)","200 Endo":"Uncommon (22.22%)","300X Circuits":"Uncommon (11.11%)","2X Medical Debt-Bond":"Uncommon (11.11%)","Garuda Neuroptics Blueprint":"Uncommon (11.11%)","Meso M3 Relic":"Uncommon (22.22%)","Synth Deconstruct":"Uncommon (11.11%)"}},{"Final Stage":{"Garuda Neuroptics Blueprint":"Uncommon (25.00%)","Meso M3 Relic":"Common (50.00%)","Synth Deconstruct":"Uncommon (25.00%)"}}]},
		{"Rotation B":[{"Stage 1":{"Unairu Lens":"Uncommon (20.00%)","200 Endo":"Common (40.00%)","300X Plastids":"Uncommon (20.00%)","2X Medical Debt-Bond":"Uncommon (20.00%)"}},{"Stage 2, Stage 3 of 4, and Stage 3 of 5":{"Unairu Lens":"Uncommon (12.50%)","200 Endo":"Uncommon (25.00%)","300X Plastids":"Uncommon (12.50%)","2X Medical Debt-Bond":"Uncommon (12.50%)","Garuda Neuroptics Blueprint":"Uncommon (12.50%)","Meso Z3 Relic":"Uncommon (25.00%)"}},{"Stage 4 of 5":{"Unairu Lens":"Uncommon (11.11%)","200 Endo":"Uncommon (22.22%)","300X Plastids":"Uncommon (11.11%)","2X Medical Debt-Bond":"Uncommon (11.11%)","Garuda Neuroptics Blueprint":"Uncommon (11.11%)","Meso Z3 Relic":"Uncommon (22.22%)","Mecha Recharge":"Uncommon (11.11%)"}},{"Final Stage":{"Garuda Neuroptics Blueprint":"Uncommon (25.00%)","Meso Z3 Relic":"Common (50.00%)","Mecha Recharge":"Uncommon (25.00%)"}}]},
		{"Rotation C":[{"Stage 1":{"Naramon Lens":"Uncommon (20.00%)","200 Endo":"Common (40.00%)","300X Rubedo":"Uncommon (20.00%)","2X Medical Debt-Bond":"Uncommon (20.00%)"}},{"Stage 2, Stage 3 of 4, and Stage 3 of 5":{"Naramon Lens":"Uncommon (12.50%)","200 Endo":"Uncommon (25.00%)","300X Rubedo":"Uncommon (12.50%)","2X Medical Debt-Bond":"Uncommon (12.50%)","Garuda Neuroptics Blueprint":"Uncommon (12.50%)","Meso E2 Relic":"Uncommon (25.00%)"}},{"Stage 4 of 5":{"Naramon Lens":"Uncommon (11.11%)","200 Endo":"Uncommon (22.22%)","300X Rubedo":"Uncommon (11.11%)","2X Medical Debt-Bond":"Uncommon (11.11%)","Garuda Neuroptics Blueprint":"Uncommon (11.11%)","Meso E2 Relic":"Uncommon (22.22%)","Tek Enhance":"Uncommon (11.11%)"}},{"Final Stage":{"Garuda Neuroptics Blueprint":"Uncommon (25.00%)","Meso E2 Relic":"Common (50.00%)","Tek Enhance":"Uncommon (25.00%)"}}]}]},{"Level 30 - 50 Orb Vallis Bounty":[
		{"Rotation A":[{"Stage 1":{"Vazarin Lens":"Uncommon (25.81%)","300 Endo":"Uncommon (25.81%)","2X Fieldron":"Uncommon (29.03%)","2X Advances Debt-Bond":"Uncommon (19.35%)"}},{"Stage 2, Stage 3 of 4, and Stage 3 of 5":{"Vazarin Lens":"Uncommon (19.75%)","300 Endo":"Uncommon (19.75%)","2X Fieldron":"Uncommon (22.22%)","2X Advances Debt-Bond":"Uncommon (14.81%)","Neo S11 Relic":"Uncommon (18.52%)","Tellurium":"Rare (4.94%)"}},{"Stage 4 of 5":{"Vazarin Lens":"Uncommon (17.58%)","300 Endo":"Uncommon (17.58%)","2X Fieldron":"Uncommon (19.78%)","2X Advances Debt-Bond":"Uncommon (13.19%)","Neo S11 Relic":"Uncommon (16.48%)","Tellurium":"Rare (4.40%)","Synth Fiber":"Uncommon (10.99%)"}},{"Final Stage":{"Neo S11 Relic":"Common (51.72%)","Tellurium":"Uncommon (13.79%)","Synth Fiber":"Common (34.48%)"}}]},
		{"Rotation B":[{"Stage 1":{"Zenurik Lens":"Uncommon (25.81%)","300 Endo":"Uncommon (25.81%)","2X Detonite Injector":"Uncommon (29.03%)","2X Advances Debt-Bond":"Uncommon (19.35%)"}},{"Stage 2, Stage 3 of 4, and Stage 3 of 5":{"Zenurik Lens":"Uncommon (19.75%)","300 Endo":"Uncommon (19.75%)","2X Detonite Injector":"Uncommon (22.22%)","2X Advances Debt-Bond":"Uncommon (14.81%)","Neo N10 Relic":"Uncommon (18.52%)","Tellurium":"Rare (4.94%)"}},{"Stage 4 of 5":{"Zenurik Lens":"Uncommon (17.58%)","300 Endo":"Uncommon (17.58%)","2X Detonite Injector":"Uncommon (19.78%)","2X Advances Debt-Bond":"Uncommon (13.19%)","Neo N10 Relic":"Uncommon (16.48%)","Tellurium":"Rare (4.40%)","Mecha Empowered":"Uncommon (10.99%)"}},{"Final Stage":{"Neo N10 Relic":"Common (51.72%)","Tellurium":"Uncommon (13.79%)","Mecha Empowered":"Common (34.48%)"}}]},
		{"Rotation C":[{"Stage 1":{"200X Kuva":"Uncommon (25.81%)","300 Endo":"Uncommon (25.81%)","2X Mutagen Mass":"Uncommon (29.03%)","2X Advances Debt-Bond":"Uncommon (19.35%)"}},{"Stage 2, Stage 3 of 4, and Stage 3 of 5":{"200X Kuva":"Uncommon (19.75%)","300 Endo":"Uncommon (19.75%)","2X Mutagen Mass":"Uncommon (22.22%)","2X Advances Debt-Bond":"Uncommon (14.81%)","Neo C1 Relic":"Uncommon (18.52%)","Tellurium":"Rare (4.94%)"}},{"Stage 4 of 5":{"200X Kuva":"Uncommon (17.58%)","300 Endo":"Uncommon (17.58%)","2X Mutagen Mass":"Uncommon (19.78%)","2X Advances Debt-Bond":"Uncommon (13.19%)","Neo C1 Relic":"Uncommon (16.48%)","Tellurium":"Rare (4.40%)","Tek Gravity":"Uncommon (10.99%)"}},{"Final Stage":{"Neo C1 Relic":"Common (51.72%)","Tellurium":"Uncommon (13.79%)","Tek Gravity":"Common (34.48%)"}}]}]},{"Level 40 - 60 Orb Vallis Bounty":[
		{"Rotation A":[{"Stage 1":{"400 Endo":"Common (50.00%)","2X Familial Debt-Bond":"Uncommon (25.00%)","10,000 Credits Cache":"Uncommon (25.00%)"}},{"Stage 2, Stage 3 of 4, and Stage 3 of 5":{"400 Endo":"Common (33.33%)","2X Familial Debt-Bond":"Uncommon (16.67%)","10,000 Credits Cache":"Uncommon (16.67%)","Axi T2 Relic":"Uncommon (25.00%)","500X Kuva":"Rare (8.33%)"}},{"Stage 4 of 5":{"400 Endo":"Uncommon (28.57%)","2X Familial Debt-Bond":"Uncommon (14.29%)","10,000 Credits Cache":"Uncommon (14.29%)","Axi T2 Relic":"Uncommon (21.43%)","500X Kuva":"Rare (7.14%)","Synth Reflex":"Uncommon (14.29%)"}},{"Final Stage":{"Axi T2 Relic":"Common (50.00%)","500X Kuva":"Uncommon (16.67%)","Synth Reflex":"Common (33.33%)"}}]},
		{"Rotation B":[{"Stage 1":{"400 Endo":"Common (50.00%)","2X Familial Debt-Bond":"Uncommon (25.00%)","10,000 Credits Cache":"Uncommon (25.00%)"}},{"Stage 2, Stage 3 of 4, and Stage 3 of 5":{"400 Endo":"Common (33.33%)","2X Familial Debt-Bond":"Uncommon (16.67%)","10,000 Credits Cache":"Uncommon (16.67%)","Axi K5 Relic":"Uncommon (25.00%)","500X Kuva":"Rare (8.33%)"}},{"Stage 4 of 5":{"400 Endo":"Uncommon (28.57%)","2X Familial Debt-Bond":"Uncommon (14.29%)","10,000 Credits Cache":"Uncommon (14.29%)","Axi K5 Relic":"Uncommon (21.43%)","500X Kuva":"Rare (7.14%)","Mecha Pulse":"Uncommon (14.29%)"}},{"Final Stage":{"Axi K5 Relic":"Common (50.00%)","500X Kuva":"Uncommon (16.67%)","Mecha Pulse":"Common (33.33%)"}}]},
		{"Rotation C":[{"Stage 1":{"400 Endo":"Common (50.00%)","Neurodes":"Uncommon (12.50%)","Orokin Cell":"Uncommon (12.50%)","2X Familial Debt-Bond":"Uncommon (25.00%)"}},{"Stage 2, Stage 3 of 4, and Stage 3 of 5":{"400 Endo":"Common (33.33%)","Neurodes":"Rare (8.33%)","Orokin Cell":"Rare (8.33%)","2X Familial Debt-Bond":"Uncommon (16.67%)","Axi T2 Relic":"Uncommon (25.00%)","500X Kuva":"Rare (8.33%)"}},{"Stage 4 of 5":{"400 Endo":"Uncommon (28.57%)","Neurodes":"Rare (7.14%)","Orokin Cell":"Rare (7.14%)","2X Familial Debt-Bond":"Uncommon (14.29%)","Axi T2 Relic":"Uncommon (21.43%)","500X Kuva":"Rare (7.14%)","Tek Collateral":"Uncommon (14.29%)"}},{"Final Stage":{"Axi T2 Relic":"Common (50.00%)","500X Kuva":"Uncommon (16.67%)","Tek Collateral":"Common (33.33%)"}}]}]},{"Level 40 - 60 PROFIT-TAKER - PHASE 1":[{"Bounty Completion":[{"Final Stage":{"5X Gyromag Systems":"Uncommon (25.00%)","Lith M4 Relic (Radiant)":"Uncommon (15.00%)","Quick Reload":"Uncommon (15.00%)","4X Atmo Systems":"Uncommon (10.00%)","3X Vega Toroid":"Uncommon (12.50%)","Lith A3 Relic (Radiant)":"Uncommon (12.50%)","3X Repeller Systems":"Rare (7.50%)","Deadly Efficiency":"Ultra Rare (1.25%)","Strain Eruption":"Ultra Rare (1.25%)"}}]}]},{"Level 40 - 60 PROFIT-TAKER - PHASE 2":[{"Bounty Completion":[{"Final Stage":{"5X Gyromag Systems":"Uncommon (25.00%)","Lith P2 Relic (Radiant)":"Uncommon (15.00%)","Resolute Focus":"Uncommon (15.00%)","4X Atmo Systems":"Uncommon (10.00%)","3X Calda Toroid":"Uncommon (12.50%)","Meso M3 Relic (Radiant)":"Uncommon (12.50%)","3X Repeller Systems":"Rare (7.50%)","Archgun Ace":"Ultra Rare (1.25%)","Strain Fever":"Ultra Rare (1.25%)"}}]}]},{"Level 40 - 60 PROFIT-TAKER - PHASE 3":[{"First Completion":[{"Final Stage":{"Gravimag":"Very Common (100.00%)"}}]},{"Subsequent Completions":[{"Final Stage":{"5X Gyromag Systems":"Uncommon (25.00%)","Meso Z3 Relic (Radiant)":"Uncommon (15.00%)","Marked Target":"Uncommon (15.00%)","4X Atmo Systems":"Uncommon (10.00%)","3X Sola Toroid":"Uncommon (12.50%)","Neo S11 Relic (Radiant)":"Uncommon (12.50%)","3X Repeller Systems":"Rare (7.50%)","Sabot Rounds":"Ultra Rare (1.25%)","Strain Infection":"Ultra Rare (1.25%)"}}]}]},{"Level 50 - 60 PROFIT-TAKER - PHASE 4":[{"Bounty Completion":[{"Final Stage":{"5X Gyromag Systems":"Uncommon (28.57%)","Neo N10 Relic (Radiant)":"Uncommon (17.14%)","Ammo Chain":"Uncommon (17.14%)","4X Atmo Systems":"Uncommon (11.43%)","Axi T2 Relic (Radiant)":"Uncommon (14.29%)","3X Repeller Systems":"Rare (8.57%)","Critical Focus":"Ultra Rare (1.43%)","Strain Consume":"Ultra Rare (1.43%)"}}]}]}]}
